unifi_mcp/__init__.py
unifi_mcp/__main__.py
unifi_mcp/cli.py
unifi_mcp/config.py
unifi_mcp/main.py
unifi_mcp/server.py
unifi_mcp/clients/access_client.py
unifi_mcp/clients/base_client.py
unifi_mcp/clients/network_client.py
unifi_mcp/models/access.py
unifi_mcp/models/network.py
unifi_mcp/tools/access_tools.py
unifi_mcp/tools/network_tools.py
unifi_mcp/utils/process_utils.py
unifi_mcp/utils/retry_utils.py
unifi_mcp-0.2.5.dist-info/licenses/LICENSE
unifi_mcp-0.2.5.dist-info/METADATA
unifi_mcp-0.2.5.dist-info/WHEEL
unifi_mcp-0.2.5.dist-info/top_level.txt
unifi_mcp-0.2.5.dist-info/RECORD
