Metadata-Version: 2.4
Name: unifi-mcp
Version: 0.2.5
Summary: Unofficial MCP server for the UniFi Site Manager, Access, and Network APIs
Author-email: Les Leslie <les@wedgwoodwebworks.com>
Requires-Python: >=3.13
License-File: LICENSE
Requires-Dist: fastmcp>=2.12.3
Requires-Dist: mcp-common>=0.4.8
Requires-Dist: oneiric>=0.3.6
Requires-Dist: pydantic[email]>=2.11.9
Dynamic: license-file
